setup.py
Shiny/__init__.py
Shiny/shiny.py
Shiny/test.py
Shiny_SDK.egg-info/PKG-INFO
Shiny_SDK.egg-info/SOURCES.txt
Shiny_SDK.egg-info/dependency_links.txt
Shiny_SDK.egg-info/requires.txt
Shiny_SDK.egg-info/top_level.txt