Metadata-Version: 1.0
Name: Shiny-SDK
Version: 1.6.3
Summary: Python SDK from Shiny.
Home-page: https://shiny.kotori.moe
Author: Eridanus Sora
Author-email: sora@sound.moe
License: MIT License
Keywords: Shiny-Project
Platform: any
